ataner.py
ataner-0.0.1.dist-info/LICENSE
ataner-0.0.1.dist-info/METADATA
ataner-0.0.1.dist-info/WHEEL
ataner-0.0.1.dist-info/top_level.txt
ataner-0.0.1.dist-info/RECORD
